{
	"info": {
		"_postman_id": "a1b2c3d4-e5f6-7a8b-9c0d-e1f2a3b4c5d6",
		"name": "Smart Factory API - Predictive Maintenance",
		"description": "Koleksi API untuk pengujian endpoint Predictive Maintenance menggunakan model Random Forest yang telah di-tune.",
		"schema": "https://schema.getpostman.com/json/collection/v2.1.0/collection.json"
	},
	"item": [
		{
			"name": "Predict Machine Failure",
			"request": {
				"method": "POST",
				"header": [
					{
						"key": "Content-Type",
						"value": "application/json",
						"type": "text"
					}
				],
				"body": {
					"mode": "raw",
					"raw": "{\n  \"air_temp\": 298.1,\n  \"process_temp\": 308.6,\n  \"rot_speed\": 1551,\n  \"torque\": 42.8,\n  \"tool_wear\": 0\n}"
				},
				"url": {
					"raw": "http://127.0.0.1:8000/predict",
					"protocol": "http",
					"host": [
						"127",
						"0",
						"0",
						"1"
					],
					"port": "8000",
					"path": [
						"predict"
					]
				},
				"description": "Endpoint untuk memprediksi kegagalan mesin berdasarkan parameter sensor operasional."
			},
			"response": []
		}
	]
}